setup.py
distribu/Binomialdistribution.py
distribu/Gaussiandistribution.py
distribu/Generaldistribution.py
distribu/__init__.py
distribu.egg-info/PKG-INFO
distribu.egg-info/SOURCES.txt
distribu.egg-info/dependency_links.txt
distribu.egg-info/not-zip-safe
distribu.egg-info/top_level.txt