Metadata-Version: 1.0
Name: distribu
Version: 0.1
Summary: Gaussian distributions
Home-page: UNKNOWN
Author: Priyanshu Arya
Author-email: priyanshucoder@gmail.com
License: UNKNOWN
Platform: UNKNOWN
